anpy/__init__.py
anpy/amendement.py
anpy/dossier.py
anpy/dossier_from_opendata.py
anpy/dossier_like_senapy.py
anpy/question.py
anpy/scrutin.py
anpy/utils.py
anpy-0.2.1.data/scripts/anpy-cli
anpy-0.2.1.dist-info/LICENSE
anpy-0.2.1.dist-info/METADATA
anpy-0.2.1.dist-info/WHEEL
anpy-0.2.1.dist-info/top_level.txt
anpy-0.2.1.dist-info/RECORD
