Metadata-Version: 2.1
Name: anpy
Version: 0.2.1
Summary: Python client for assemblee-nationale.fr website
Home-page: https://github.com/regardscitoyens/anpy
Author: Regards Citoyens
Author-email: contact@regardscitoyens.org
License: MIT
Keywords: scraping politics data
Platform: UNKNOWN
Classifier: Development Status :: 3 - Alpha
Classifier: License :: OSI Approved :: MIT License
Classifier: Operating System :: OS Independent
Classifier: Programming Language :: Python :: 3
Requires-Dist: pathlib (<1.1,>=1.0)
Requires-Dist: click (<6.8,>=6.7)
Requires-Dist: xmltodict (<0.12,>=0.11)
Requires-Dist: html5lib (<1.1,>=1.0)
Requires-Dist: html2text (==2018.1.9)
Requires-Dist: mistune (<0.9,>=0.8)
Requires-Dist: dateparser (<0.8,>=0.7)
Requires-Dist: attrs (<19.2,>=19.1)
Requires-Dist: future (<0.17,>=0.16)
Requires-Dist: lawfactory-utils
